{
    "option.svDeleteReplyBan.txt": {
        "global_cache": false,
        "version_id": 2010000,
        "version_string": "2.1.0",
        "hash": "58b4ca0ae5c743881de713de7713523d"
    },
    "option.svEditReplyBan.txt": {
        "global_cache": false,
        "version_id": 2010000,
        "version_string": "2.1.0",
        "hash": "13762da47fe0e1e9faaf58989c56bace"
    },
    "option.svLikeReplyBan.txt": {
        "global_cache": false,
        "version_id": 2010000,
        "version_string": "2.1.0",
        "hash": "e1bfbf0f7271b1a55009780bef4723f8"
    },
    "option.svThreadmarkReplyBan.txt": {
        "global_cache": false,
        "version_id": 2010000,
        "version_string": "2.1.0",
        "hash": "1036b7db98a8ffa962b350bed518d1fe"
    },
    "option_explain.svDeleteReplyBan.txt": {
        "global_cache": false,
        "version_id": 2010000,
        "version_string": "2.1.0",
        "hash": "7d92bc103a065f74d9d29b5afc724d98"
    },
    "option_explain.svEditReplyBan.txt": {
        "global_cache": false,
        "version_id": 2010000,
        "version_string": "2.1.0",
        "hash": "4dcb868e23a6af99b9519ad7fcf240db"
    },
    "option_explain.svLikeReplyBan.txt": {
        "global_cache": false,
        "version_id": 2010000,
        "version_string": "2.1.0",
        "hash": "2b1e9e021283c0f201ea82d7eacfe8a6"
    },
    "option_explain.svThreadmarkReplyBan.txt": {
        "global_cache": false,
        "version_id": 2010000,
        "version_string": "2.1.0",
        "hash": "e820798b8f38d382fd724fafda3f6497"
    },
    "option_group.SV_ThreadReplyBanTeeth.txt": {
        "global_cache": false,
        "version_id": 1000031,
        "version_string": "1.0.0 Beta 1",
        "hash": "b54bde815fc93abfc43bf8482a38ac84"
    },
    "option_group_description.SV_ThreadReplyBanTeeth.txt": {
        "global_cache": false,
        "version_id": 2000070,
        "version_string": "2.0.0",
        "hash": "c149afa9c657f92c772c9334f1cedc60"
    }
}